mlconjug/PyVerbiste.py
mlconjug/PyVerbiste.pyi
mlconjug/__init__.py
mlconjug/__init__.pyi
mlconjug/cli.py
mlconjug/cli.pyi
mlconjug/mlconjug.py
mlconjug/mlconjug.pyi
mlconjug/py.typed
mlconjug/data/conjug_manager/conjugation-en.json
mlconjug/data/conjug_manager/conjugation-en.xml
mlconjug/data/conjug_manager/conjugation-es.json
mlconjug/data/conjug_manager/conjugation-es.xml
mlconjug/data/conjug_manager/conjugation-fr.json
mlconjug/data/conjug_manager/conjugation-fr.xml
mlconjug/data/conjug_manager/conjugation-it.json
mlconjug/data/conjug_manager/conjugation-it.xml
mlconjug/data/conjug_manager/conjugation-pt.json
mlconjug/data/conjug_manager/conjugation-pt.xml
mlconjug/data/conjug_manager/conjugation-ro.json
mlconjug/data/conjug_manager/conjugation-ro.xml
mlconjug/data/conjug_manager/verbiste-es-en-it-pt-ro.zip
mlconjug/data/conjug_manager/verbs-en.json
mlconjug/data/conjug_manager/verbs-en.xml
mlconjug/data/conjug_manager/verbs-es.json
mlconjug/data/conjug_manager/verbs-es.xml
mlconjug/data/conjug_manager/verbs-fr.json
mlconjug/data/conjug_manager/verbs-fr.xml
mlconjug/data/conjug_manager/verbs-it.json
mlconjug/data/conjug_manager/verbs-it.xml
mlconjug/data/conjug_manager/verbs-pt.json
mlconjug/data/conjug_manager/verbs-pt.xml
mlconjug/data/conjug_manager/verbs-ro.json
mlconjug/data/conjug_manager/verbs-ro.xml
mlconjug/data/models/trained_model-en-final.zip
mlconjug/data/models/trained_model-es-final.zip
mlconjug/data/models/trained_model-fr-final.zip
mlconjug/data/models/trained_model-it-final.zip
mlconjug/data/models/trained_model-pt-final.zip
mlconjug/data/models/trained_model-ro-final.zip
mlconjug/locale/es/LC_MESSAGES/PyVerbiste.mo
mlconjug/locale/es/LC_MESSAGES/PyVerbiste.po
mlconjug/locale/es/LC_MESSAGES/cli.mo
mlconjug/locale/es/LC_MESSAGES/cli.po
mlconjug/locale/es/LC_MESSAGES/mlconjug.mo
mlconjug/locale/es/LC_MESSAGES/mlconjug.po
mlconjug/locale/fr/LC_MESSAGES/PyVerbiste.mo
mlconjug/locale/fr/LC_MESSAGES/PyVerbiste.po
mlconjug-3.4.0.dist-info/AUTHORS.rst
mlconjug-3.4.0.dist-info/LICENSE
mlconjug-3.4.0.dist-info/METADATA
mlconjug-3.4.0.dist-info/WHEEL
mlconjug-3.4.0.dist-info/entry_points.txt
mlconjug-3.4.0.dist-info/top_level.txt
mlconjug-3.4.0.dist-info/RECORD
