Metadata-Version: 2.1
Name: mlconjug
Version: 3.4.0
Summary: A Python library to conjugate French, English, Spanish, Italian, Portuguese and Romanian verbs using Machine Learning techniques.
Home-page: https://github.com/SekouD/mlconjug
Author: SekouD
Author-email: sekoud.python@gmail.com
License: MIT license
Keywords: mlconjug conjugate conjugator conjugation conjugaison conjugación coniugazione conjugação conjugare verbs verbes verbos ML machine-learning NLP linguistics linguistique linguistica conjug_manager sklearnscikit-learn
Platform: UNKNOWN
Classifier: Development Status :: 5 - Production/Stable
Classifier: Topic :: Software Development :: Libraries :: Python Modules
Classifier: Topic :: Education
Classifier: Topic :: Scientific/Engineering :: Artificial Intelligence
Classifier: Topic :: Utilities
Classifier: Intended Audience :: Developers
Classifier: Intended Audience :: End Users/Desktop
Classifier: Intended Audience :: Education
Classifier: Intended Audience :: Science/Research
Classifier: License :: OSI Approved :: MIT License
Classifier: Natural Language :: English
Classifier: Natural Language :: French
Classifier: Natural Language :: Spanish
Classifier: Natural Language :: Italian
Classifier: Natural Language :: Portuguese
Classifier: Natural Language :: Romanian
Classifier: Operating System :: OS Independent
Classifier: Programming Language :: Python :: 3
Classifier: Programming Language :: Python :: 3.3
Classifier: Programming Language :: Python :: 3.4
Classifier: Programming Language :: Python :: 3.5
Classifier: Programming Language :: Python :: 3.6
Classifier: Programming Language :: Python :: 3.7
Requires-Dist: cython
Requires-Dist: Click (>=6.0)
Requires-Dist: numpy
Requires-Dist: scipy
Requires-Dist: scikit-learn (>=0.20.2)
